pter/__init__.py
pter/autotemplate.py
pter/common.py
pter/configuration.py
pter/curses.py
pter/help.py
pter/hook.py
pter/key.py
pter/main.py
pter/qtui.py
pter/searcher.py
pter/source.py
pter/tr.py
pter/utils.py
pter/version.py
pter/docs/pter.config.html
pter/docs/pter.html
pter/docs/qpter.html
pter/icons/qpter_16x16.png
pter/icons/qpter_32x32.png
pter-3.21.0.data/data/share/man/man1/pter.1
pter-3.21.0.data/data/share/man/man1/qpter.1
pter-3.21.0.data/data/share/man/man5/pter.config.5
pter-3.21.0.dist-info/licenses/AUTHORS.md
pter-3.21.0.dist-info/licenses/LICENSE
pter-3.21.0.dist-info/METADATA
pter-3.21.0.dist-info/WHEEL
pter-3.21.0.dist-info/entry_points.txt
pter-3.21.0.dist-info/top_level.txt
pter-3.21.0.dist-info/RECORD
