Metadata-Version: 2.4
Name: pter
Version: 3.21.0
Summary: Console UI to manage your todo.txt file(s).
Author-email: R <contact+pter@vonshednob.cc>
License: MIT License
Project-URL: repository, https://codeberg.org/vonshednob/pter
Project-URL: changelog, https://codeberg.org/vonshednob/pter/src/branch/main/CHANGELOG.md
Project-URL: bugs, https://codeberg.org/vonshednob/pter/issues
Project-URL: issues, https://github.com/vonshednob/pter/issues
Classifier: Development Status :: 5 - Production/Stable
Classifier: Environment :: Console :: Curses
Classifier: Intended Audience :: End Users/Desktop
Classifier: License :: OSI Approved :: MIT License
Classifier: Natural Language :: English
Classifier: Programming Language :: Python :: 3
Requires-Python: >=3.8
License-File: LICENSE
License-File: AUTHORS.md
Requires-Dist: pytodotxt>=2.0.0
Requires-Dist: cursedspace>=1.3.1
Provides-Extra: xdg
Requires-Dist: pyxdg; extra == "xdg"
Provides-Extra: qt
Requires-Dist: PyQt5; extra == "qt"
Provides-Extra: qtdark
Requires-Dist: QDarkStyle; extra == "qtdark"
Provides-Extra: all
Requires-Dist: pyxdg; extra == "all"
Requires-Dist: PyQt5; extra == "all"
Requires-Dist: QDarkStyle; extra == "all"
Dynamic: license-file
